qvpnstatus/__init__.py
qvpnstatus/__main__.py
qvpnstatus/cli.py
qvpnstatus/images/active_shield.png
qvpnstatus/images/edit-copy.png
qvpnstatus/images/edit-cut.png
qvpnstatus/images/edit-paste.png
qvpnstatus/images/exit.png
qvpnstatus/images/inactive_shield.png
qvpnstatus/images/logo.png
qvpnstatus/main.py
qvpnstatus/settings.py
qvpnstatus/sounds/364658__original-sound__notification.wav
qvpnstatus/sounds/514152__edwardszakal__alert.wav
qvpnstatus/sounds/538149__fupicat__notification.wav
qvpnstatus/systemtraystatus.py
qvpnstatus-0.1.2.dist-info/entry_points.txt
qvpnstatus-0.1.2.dist-info/LICENSE
qvpnstatus-0.1.2.dist-info/WHEEL
qvpnstatus-0.1.2.dist-info/METADATA
qvpnstatus-0.1.2.dist-info/RECORD
