Metadata-Version: 2.1
Name: qvpnstatus
Version: 0.1.2
Summary: VPN Status tray icon for monitoring VPN connection
Home-page: https://gitlab.com/mikeramsey/qvpnstatus
License: MIT
Keywords: vpn,status,monitoring,nmcli
Author: Michael Ramsey
Author-email: mike@hackerdise.me
Requires-Python: >=3.7,<4.0
Classifier: License :: OSI Approved :: MIT License
Classifier: Programming Language :: Python :: 3
Classifier: Programming Language :: Python :: 3.7
Classifier: Programming Language :: Python :: 3.8
Classifier: Programming Language :: Python :: 3.9
Requires-Dist: PyQt5 (==5.15.2)
Requires-Dist: PyQt5-sip (==12.8.1)
Requires-Dist: PyQt5-stubs (==5.14.2.2)
Requires-Dist: fbs (==0.9.0)
Requires-Dist: nmcli (>=0.5.0,<0.6.0)
Requires-Dist: psutil (>=5.8.0,<6.0.0)
Project-URL: Repository, https://gitlab.com/mikeramsey/qvpnstatus
